{
  "project_info": {
    "project_number": "425247730307",
    "firebase_url": "https://stamp-db6ad-default-rtdb.europe-west1.firebasedatabase.app",
    "project_id": "stamp-db6ad",
    "storage_bucket": "stamp-db6ad.appspot.com"
  },
  "client": [
    {
      "client_info": {
        "mobilesdk_app_id": "1:425247730307:android:868d37dbc94d4c61ad09b6",
        "android_client_info": {
          "package_name": "com.grupp6.stamp_app"
        }
      },
      "oauth_client": [
        {
          "client_id": "425247730307-e04udjp02t64nhom6uidmegsepreru9j.apps.googleusercontent.com",
          "client_type": 3
        }
      ],
      "api_key": [
        {
          "current_key": "AIzaSyAC0hqSCNJ5SrfNo5h-DOk_ohaviEq5VdQ"
        }
      ],
      "services": {
        "appinvite_service": {
          "other_platform_oauth_client": [
            {
              "client_id": "425247730307-e04udjp02t64nhom6uidmegsepreru9j.apps.googleusercontent.com",
              "client_type": 3
            }
          ]
        }
      }
    }
  ],
  "configuration_version": "1"
}